<?xml version="1.0" encoding="UTF-8"?>
<addon id="skin.xperience1080" version="0.9.1" name="Xperience1080" provider-name="Black">
	<requires>
		<import addon="xbmc.gui" version="3.00"/>
		<import addon="script.logo-downloader" version="2.0.0"/>
	</requires>
	<extension point="xbmc.gui.skin" defaultthemename="Textures.xbt" effectslowdown="1.00" debugging="false">
		<res width="1920" height="1080" aspect="16:9" default="true" folder="1080i" />
	</extension>
	<extension point="xbmc.addon.metadata">
		<platform>all</platform>
		<minversion app="xbmc">28000</minversion>
		<summary>Black's 1080p mod of the Xperience skin</summary>
		<description></description>
		<disclaimer></disclaimer>
	</extension>
</addon>

